wystia/__init__.py
wystia/api_base.py
wystia/api_data.py
wystia/api_embed.py
wystia/api_helper.py
wystia/api_upload.py
wystia/config.py
wystia/constants.py
wystia/errors.py
wystia/log.py
wystia/models.py
wystia/requests_config.py
wystia/requests_models.py
wystia/utils/__init__.py
wystia/utils/decorators.py
wystia/utils/metaclasses.py
wystia/utils/response.py
wystia/utils/parse/__init__.py
wystia/utils/parse/file.py
wystia/utils/parse/srt.py
wystia/utils/parse/types.py
wystia-1.2.2.dist-info/LICENSE
wystia-1.2.2.dist-info/METADATA
wystia-1.2.2.dist-info/WHEEL
wystia-1.2.2.dist-info/top_level.txt
wystia-1.2.2.dist-info/RECORD
