Metadata-Version: 1.2
Name: wystia
Version: 1.2.2
Summary: A Python wrapper library for the Wistia API
Home-page: https://github.com/rnag/wystia
Author: Ritvik Nag
Author-email: rv.kvetch@gmail.com
License: MIT
Keywords: wistia,api,wrapper,data api,upload api
Platform: UNKNOWN
Classifier: Development Status :: 5 - Production/Stable
Classifier: Intended Audience :: Developers
Classifier: License :: OSI Approved :: MIT License
Classifier: Natural Language :: English
Classifier: Operating System :: OS Independent
Classifier: Programming Language :: Python :: 3 :: Only
Classifier: Programming Language :: Python :: 3
Classifier: Programming Language :: Python :: 3.7
Classifier: Programming Language :: Python :: 3.8
Classifier: Programming Language :: Python :: 3.9
Classifier: Programming Language :: Python :: 3.10
Classifier: Programming Language :: Python :: 3.11
Classifier: Programming Language :: Python
Requires-Python: >=3.7
